app/__init__.py
app/autoencoder_model.py
app/config.py
app/gcn_layer.py
app/gcn_model.py
app/routes.py
app/transformer.py
breast_substype_analysis-1.1.0.dist-info/LICENSE
breast_substype_analysis-1.1.0.dist-info/METADATA
breast_substype_analysis-1.1.0.dist-info/WHEEL
breast_substype_analysis-1.1.0.dist-info/entry_points.txt
breast_substype_analysis-1.1.0.dist-info/top_level.txt
breast_substype_analysis-1.1.0.dist-info/RECORD
