Metadata-Version: 2.1
Name: breast-substype-analysis
Version: 1.1.0
Summary: breast-subtype-analysis 是一个用于乳腺癌症分子分型预测的Python包。
Author: xia shufan
Author-email: 2757462803@qq.com
Classifier: Development Status :: 3 - Alpha
Classifier: Intended Audience :: Developers
Classifier: License :: OSI Approved :: MIT License
Classifier: Programming Language :: Python :: 3
Classifier: Programming Language :: Python :: 3.6
Classifier: Programming Language :: Python :: 3.7
Classifier: Programming Language :: Python :: 3.8
License-File: LICENSE
Requires-Dist: Flask (==2.2.3)
Requires-Dist: matplotlib (==3.5.3)
Requires-Dist: model-log (==1.2.0)
Requires-Dist: numpy (==1.21.6)
Requires-Dist: pandas (==1.3.0)
Requires-Dist: pandas-stubs (==1.2.0.62)
Requires-Dist: scikit-learn (==1.0.1)
Requires-Dist: setuptools (==65.5.0)
Requires-Dist: snfpy (==0.2.2)
Requires-Dist: torch (==1.13.0)
Requires-Dist: torchviz (==0.0.2)
Requires-Dist: tqdm (==4.64.1)
Requires-Dist: Werkzeug (==2.2.3)
